pyproject.toml
.github/workflows/tests/release-dry-run.json
.github/workflows/tests/scenario-evaluation-config.json
armory/__about__.py
armory/__init__.py
armory/__main__.py
armory/arguments.py
armory/configuration.py
armory/delayed_imports.py
armory/environment.py
armory/logs.py
armory/paths.py
armory/art_experimental/__init__.py
armory/art_experimental/attacks/__init__.py
armory/art_experimental/attacks/carla_adversarial_texture.py
armory/art_experimental/attacks/carla_mot_adversarial_patch.py
armory/art_experimental/attacks/carla_mot_patch.py
armory/art_experimental/attacks/carla_obj_det_adversarial_patch.py
armory/art_experimental/attacks/carla_obj_det_patch.py
armory/art_experimental/attacks/carla_obj_det_utils.py
armory/art_experimental/attacks/cascading_attack.py
armory/art_experimental/attacks/dapricot_patch.py
armory/art_experimental/attacks/fgm_binary_search.py
armory/art_experimental/attacks/frame.py
armory/art_experimental/attacks/gradient_matching.py
armory/art_experimental/attacks/kenansville_dft.py
armory/art_experimental/attacks/patch.py
armory/art_experimental/attacks/pgd_patch.py
armory/art_experimental/attacks/poison_loader_audio.py
armory/art_experimental/attacks/poison_loader_clbd.py
armory/art_experimental/attacks/poison_loader_dlbd.py
armory/art_experimental/attacks/poison_loader_obj_det.py
armory/art_experimental/attacks/robust_dpatch.py
armory/art_experimental/attacks/snr_pgd.py
armory/art_experimental/attacks/sweep.py
armory/art_experimental/attacks/video_frame_border.py
armory/art_experimental/defences/__init__.py
armory/art_experimental/defences/base.py
armory/art_experimental/defences/jpeg_compression_multichannel_image.py
armory/art_experimental/defences/jpeg_compression_normalized.py
armory/art_experimental/defences/random_affine_pytorch.py
armory/art_experimental/defences/transformer.py
armory/art_experimental/defences/video_compression_normalized.py
armory/art_experimental/poison_detection/__init__.py
armory_testbed-0.19.2.dist-info/METADATA
armory_testbed-0.19.2.dist-info/WHEEL
armory_testbed-0.19.2.dist-info/entry_points.txt
armory_testbed-0.19.2.dist-info/licenses/LICENSE
armory_testbed-0.19.2.dist-info/RECORD
