Metadata-Version: 2.1
Name: armory-testbed
Version: 0.19.2
Summary: Adversarial Robustness Test Bed
Project-URL: Source, https://github.com/twosixlabs/armory
Project-URL: Documentation, https://github.com/twosixlabs/armory
Author-email: Two Six Technologies <armory@twosixtech.com>
License-Expression: MIT
License-File: LICENSE
Classifier: Development Status :: 3 - Alpha
Classifier: Environment :: Console
Classifier: Intended Audience :: Developers
Classifier: Intended Audience :: Education
Classifier: Intended Audience :: Science/Research
Classifier: License :: OSI Approved :: MIT License
Classifier: Natural Language :: English
Classifier: Programming Language :: Python :: 3.8
Classifier: Programming Language :: Python :: 3.9
Classifier: Programming Language :: Python :: 3.10
Classifier: Topic :: Scientific/Engineering :: Artificial Intelligence
Requires-Python: >=3.8
Requires-Dist: cairosvg
Requires-Dist: docker
Requires-Dist: jsonschema
Requires-Dist: loguru
Requires-Dist: matplotlib
Requires-Dist: pillow
Requires-Dist: pytest
Requires-Dist: requests
Requires-Dist: setuptools-scm
Requires-Dist: svg-py
Provides-Extra: all
Requires-Dist: armory-testbed[datasets]; extra == 'all'
Requires-Dist: armory-testbed[developer]; extra == 'all'
Requires-Dist: armory-testbed[engine]; extra == 'all'
Requires-Dist: armory-testbed[jupyter]; extra == 'all'
Requires-Dist: armory-testbed[math]; extra == 'all'
Requires-Dist: armory-testbed[pytorch]; extra == 'all'
Requires-Dist: armory-testbed[tensorflow]; extra == 'all'
Provides-Extra: datasets
Requires-Dist: armory-testbed[tensorflow]; extra == 'datasets'
Requires-Dist: protobuf; extra == 'datasets'
Requires-Dist: tensorflow-datasets!=4.9.0,>=4.6.0; extra == 'datasets'
Provides-Extra: datasets-builder
Requires-Dist: apache-beam>=2.22.0; extra == 'datasets-builder'
Requires-Dist: armory-testbed[datasets,engine]; extra == 'datasets-builder'
Provides-Extra: deepspeech
Requires-Dist: armory-testbed[datasets,engine,math,pytorch]; extra == 'deepspeech'
Requires-Dist: google-cloud-storage; extra == 'deepspeech'
Requires-Dist: hydra-core; extra == 'deepspeech'
Requires-Dist: librosa; extra == 'deepspeech'
Requires-Dist: python-levenshtein; extra == 'deepspeech'
Requires-Dist: pytorch-lightning<1.5.0; extra == 'deepspeech'
Requires-Dist: sox; extra == 'deepspeech'
Requires-Dist: torchmetrics<0.8.0; extra == 'deepspeech'
Requires-Dist: transformers; extra == 'deepspeech'
Provides-Extra: developer
Requires-Dist: bandit[toml]; extra == 'developer'
Requires-Dist: black[jupyter]==22.*; extra == 'developer'
Requires-Dist: flake8; extra == 'developer'
Requires-Dist: hatch; extra == 'developer'
Requires-Dist: hydra-core; extra == 'developer'
Requires-Dist: isort; extra == 'developer'
Requires-Dist: wheel; extra == 'developer'
Provides-Extra: engine
Requires-Dist: adversarial-robustness-toolbox==1.16.0; extra == 'engine'
Requires-Dist: boto3; extra == 'engine'
Requires-Dist: botocore; extra == 'engine'
Requires-Dist: ffmpeg-python; extra == 'engine'
Requires-Dist: opencv-python-headless==4.5.5.62; extra == 'engine'
Requires-Dist: opencv-python==4.5.5.62; extra == 'engine'
Requires-Dist: pillow; extra == 'engine'
Requires-Dist: pydub; extra == 'engine'
Requires-Dist: tensorboardx; extra == 'engine'
Requires-Dist: tidecv; extra == 'engine'
Provides-Extra: jupyter
Requires-Dist: ipywidgets; extra == 'jupyter'
Requires-Dist: jupyterlab; extra == 'jupyter'
Requires-Dist: jupyterlab-widgets; extra == 'jupyter'
Provides-Extra: math
Requires-Dist: matplotlib; extra == 'math'
Requires-Dist: numpy; extra == 'math'
Requires-Dist: pandas; extra == 'math'
Requires-Dist: scikit-learn<1.2.0,>=0.22.2; extra == 'math'
Requires-Dist: scipy>=1.4.1; extra == 'math'
Provides-Extra: pytorch
Requires-Dist: armory-testbed[datasets,engine,math]; extra == 'pytorch'
Requires-Dist: torch<=1.13.1,>=1.12.0; extra == 'pytorch'
Requires-Dist: torchaudio; extra == 'pytorch'
Requires-Dist: torchvision; extra == 'pytorch'
Provides-Extra: tensorflow
Requires-Dist: armory-testbed[datasets,engine,math]; extra == 'tensorflow'
Requires-Dist: tensorflow; extra == 'tensorflow'
Requires-Dist: tf-models-official>=2.13.1; extra == 'tensorflow'
Provides-Extra: yolo
Requires-Dist: armory-testbed[engine]; extra == 'yolo'
Requires-Dist: armory-testbed[tensorflow]; extra == 'yolo'
Requires-Dist: numpy==1.23.4; extra == 'yolo'
Requires-Dist: pytorchyolo; extra == 'yolo'
